COPYRIGHT
MANIFEST.in
Makefile
README
setup.cfg
setup.py
test/__init__.py
test/test_compile.py
test/test_status.py
tiddlywebplugins/__init__.py
tiddlywebplugins/status.py
tiddlywebplugins.status.egg-info/PKG-INFO
tiddlywebplugins.status.egg-info/SOURCES.txt
tiddlywebplugins.status.egg-info/dependency_links.txt
tiddlywebplugins.status.egg-info/namespace_packages.txt
tiddlywebplugins.status.egg-info/not-zip-safe
tiddlywebplugins.status.egg-info/requires.txt
tiddlywebplugins.status.egg-info/top_level.txt