Metadata-Version: 1.0
Name: tiddlywebplugins.status
Version: 0.8
Summary: A TiddlyWeb plugin that provides information on the current user.
Home-page: http://pypi.python.org/pypi/tiddlywebplugins.status
Author: Chris Dent
Author-email: cdent@peermore.com
License: UNKNOWN
Platform: Posix; MacOS X; Windows
